[
  {
    "lights": [
      {
        "data": {
          "color": [
            226,
            140,
            63
          ],
          "fade": 0.4,
          "flags": "IgnoreScale|NoExternalEmittance|Shadow",
          "light": "DefaultTorch01",
          "radius": 2048.0,
          "shadowDepthBias": 26.0
        },
        "points": [
          [
            0,
            0,
            500
          ]
        ]
      }
    ],
    "models": [
      "clutter\\giant\\giantcampfire01burning.nif",
      "clutter\\giant\\giantcampfire01burningnoland.nif",
      "clutter\\giant\\wbbcfgiantcampfire01burning.nif",
      "clutter\\giant\\wbbcfgiantcampfire01burningnoland.nif"
    ]
  },
  {
    "lights": [
      {
        "data": {
          "color": [
            226,
            140,
            63
          ],
          "fade": 0.5,
          "flags": "IgnoreScale|NoExternalEmittance|Shadow",
          "light": "DefaultTorch01",
          "radius": 512.0,
          "shadowDepthBias": 26.0
        },
        "points": [
          [
            0,
            0,
            75
          ]
        ],
        "whiteList": [
          "0x035f49",
          "0x03cc7b",
          "0x07569d",
          "0x0bec32",
          "0x0c5449",
          "0x0cb94a"
        ]
      }
    ],
    "models": [
      "clutter\\woodfires\\campfire01burning.nif",
      "clutter\\woodfires\\campfire01landburning.nif",
      "clutter\\woodfires\\cookingstand01.nif",
      "clutter\\woodfires\\fireplacewood01burning.nif",
      "clutter\\woodfires\\wbbcfcampfire01burning.nif",
      "clutter\\woodfires\\wbbcfcampfire01landburning.nif",
      "rest by campfire\\rbc_campfire_burning.nif",
      "rest by campfire\\rbc_campfire_landburning.nif"
    ]
  },
  {
    "lights": [
      {
        "data": {
          "color": [
            29,
            115,
            192
          ],
          "fade": 1.0,
          "flags": "IgnoreScale|NoExternalEmittance|Shadow",
          "light": "AzuraBlue01",
          "radius": 386.0,
          "shadowDepthBias": 26.0
        },
        "points": [
          [
            0,
            0,
            50
          ]
        ],
        "whiteList": []
      }
    ],
    "models": [
      "effects\\c06fxfirebluewithembersheavy.nif",
      "dlc01\\effects\\dlc1falmervalleybrazierlight.nif"
    ]
  },
  {
    "lights": [
      {
        "data": {
          "color": [
            226,
            140,
            63
          ],
          "fade": 1.0,
          "flags": "IgnoreScale|NoExternalEmittance|Shadow",
          "light": "DefaultTorch01",
          "radius": 512.0,
          "shadowDepthBias": 26.0
        },
        "points": [
          [
            0,
            150,
            100
          ]
        ],
        "whiteList": []
      }
    ],
    "models": [
      "clutter\\blacksmith\\blacksmithforge01\\blacksmithforge01.nif",
      "dlc02\\architecture\\ravenrock\\dlc2blacksmithforge01rr.nif",
      "furniture\\blacksmithforgemarker.nif",
      "furniture\\blacksmithforgemarkerwr.nif",
      "furniture\\orcfurniture\\orcblacksmithforgemarker.nif"
    ]
  },
  {
    "lights": [
      {
        "data": {
          "color": [
            226,
            140,
            63
          ],
          "fade": 1.5,
          "flags": "IgnoreScale|NoExternalEmittance|Shadow",
          "light": "DefaultTorch01",
          "radius": 768.0,
          "shadowDepthBias": 26.0
        },
        "points": [
          [
            0,
            0,
            150
          ]
        ]
      }
    ],
    "models": [
      "dlc02\\landscape\\dlc2firecrater02.nif",
      "dlc02\\landscape\\dlc2firecraterround.nif"
    ]
  },
  {
    "lights": [
      {
        "data": {
          "color": [
            226,
            140,
            63
          ],
          "fade": 1.0,
          "flags": "IgnoreScale|NoExternalEmittance|Shadow",
          "light": "DefaultTorch01",
          "radius": 512.0,
          "shadowDepthBias": 26.0
        },
        "points": [
          [
            0,
            0,
            50
          ]
        ],
        "whiteList": [
          "0x016da5",
          "0x078039",
          "0x07803b",
          "0x0dcc21",
          "0x0dfb35",
          "0x0fff1f",
          "0x102824"
        ]
      }
    ],
    "models": [
      "effects\\fxfirepit01.nif",
      "effects\\fxfiresovngarde.nif",
      "effects\\fxfirewithembers01.nif",
      "effects\\fxfirewithembers01_cheap.nif",
      "effects\\fxfirewithembers01_lite.nif",
      "effects\\fxfirewithembers02.nif",
      "effects\\fxfirewithembers02toggle.nif",
      "effects\\fxfirewithembers04.nif",
      "effects\\fxfirewithembers05.nif",
      "effects\\fxfirewithembersheavytoggle.nif",
      "effects\\fxfirewithemberslogs01.nif",
      "effects\\fxfirewithemberslogs03.nif",
      "effects\\fxfirewithemberslogs04.nif"
    ]
  },
  {
    "lights": [
      {
        "data": {
          "color": [
            20,
            0,
            150
          ],
          "fade": 0.6,
          "flags": "IgnoreScale|NoExternalEmittance|Shadow",
          "light": "DLC01SCPurple",
          "radius": 768.0,
          "shadowDepthBias": 26.0
        },
        "points": [
          [
            0,
            0,
            50
          ]
        ],
        "whiteList": []
      }
    ],
    "models": [
      "effects\\tg09nocturnalfxfirepurple.nif"
    ]
  },
  {
    "lights": [
      {
        "data": {
          "color": [
            226,
            140,
            63
          ],
          "fade": 1.0,
          "flags": "IgnoreScale|NoExternalEmittance|Shadow",
          "light": "DefaultTorch01",
          "radius": 512.0,
          "shadowDepthBias": 26.0
        },
        "points": [
          [
            0,
            250,
            50
          ]
        ],
        "whiteList": []
      }
    ],
    "models": [
      "furniture\\blacksmithingskyforgemarker.nif"
    ]
  }
]
